amahapp/__init__.py
amahapp/admin.py
amahapp/apps.py
amahapp/middleware.py
amahapp/models.py
amahapp/tests.py
amahapp/views.py
amahapp/migrations/__init__.py
django_amahapp-0.4.0.dist-info/METADATA
django_amahapp-0.4.0.dist-info/WHEEL
django_amahapp-0.4.0.dist-info/top_level.txt
django_amahapp-0.4.0.dist-info/RECORD
