Metadata-Version: 2.4
Name: django-amahapp
Version: 0.4.0
Summary: Application Django pour tracer l’activité des utilisateurs
Home-page: https://github.com/tonpseudo/django-amahapp
Author: Esther Kouao
Author-email: estherkouao@gmail.com
License: MIT
Classifier: Framework :: Django
Classifier: Programming Language :: Python :: 3
Classifier: License :: OSI Approved :: MIT License
Classifier: Operating System :: OS Independent
Requires-Python: >=3.6
Requires-Dist: Django>=3.2.4
Dynamic: author
Dynamic: author-email
Dynamic: classifier
Dynamic: description
Dynamic: description-content-type
Dynamic: home-page
Dynamic: license
Dynamic: requires-dist
Dynamic: requires-python
Dynamic: summary
